Workbook

Sheet Предпосылки
A1: Параметр | B1: Значение | C1: Единица
A2: Налоговая ставка | B2: 0.2 | C2: %
A3: Темп роста | B3: 0.15 | C3: %
A4: WACC | B4: 0.18 | C4: %
A5: Средний чек | B5: 1500 | C5: тенге
A6: Количество мест | B6: 20 | C6: шт
A7: Часы работы в день | B7: 12 | C7: часов
A8: Дней в году | B8: 365 | C8: дней
A9: Заполняемость зала | B9: 0.6 | C9: %
A10: Себестоимость продуктов | B10: 0.35 | C10: % от выручки
A11: Операционные расходы | B11: 0.25 | C11: % от выручки

Sheet Выручка
A1: Показатель | B1: Год 1 | C1: Год 2 | D1: Год 3 | E1: Год 4 | F1: Год 5
A2: Посетителей в день, человек | B2: =ROUND(assumptions!B6*assumptions!B9) | C2: =ROUND(B2*1.15) | D2: =ROUND(C2*1.15) | E2: =ROUND(D2*1.15) | F2: =ROUND(E2*1.15)
A3: Средний чек, тенге | B3: =assumptions!B5 | C3: =B3*1.05 | D3: =C3*1.05 | E3: =D3*1.05 | F3: =E3*1.05
A4: Выручка в день, тенге | B4: =B2*B3 | C4: =C2*C3 | D4: =D2*D3 | E4: =E2*E3 | F4: =F2*F3
A5: Выручка в месяц, тенге | B5: =B4*30 | C5: =C4*30 | D5: =D4*30 | E5: =E4*30 | F5: =F4*30
A6: Выручка в год, тенге | B6: =B5*12 | C6: =C5*12 | D6: =D5*12 | E6: =E5*12 | F6: =F5*12

Sheet Расходы
A1: Статья расходов | B1: Год 1 | C1: Год 2 | D1: Год 3 | E1: Год 4 | F1: Год 5
A2: Себестоимость продуктов, тенге | B2: =revenue!B6*assumptions!B10 | C2: =revenue!C6*assumptions!B10 | D2: =revenue!D6*assumptions!B10 | E2: =revenue!E6*assumptions!B10 | F2: =revenue!F6*assumptions!B10
A3: Аренда помещения, тенге | B3: 6000000 | C3: 6300000 | D3: 6615000 | E3: 6945750 | F3: 7293038
A4: Фонд оплаты труда, тенге | B4: 3600000 | C4: 3960000 | D4: 4356000 | E4: 4791600 | F4: 5270760
A5: Коммунальные услуги, тенге | B5: 360000 | C5: 378000 | D5: 396900 | E5: 416745 | F5: 437582
A6: Маркетинг и реклама, тенге | B6: =revenue!B6*0.02 | C6: =revenue!C6*0.02 | D6: =revenue!D6*0.02 | E6: =revenue!E6*0.02 | F6: =revenue!F6*0.02
A7: Прочие операционные расходы, тенге | B7: =revenue!B6*0.03 | C7: =revenue!C6*0.03 | D7: =revenue!D6*0.03 | E7: =revenue!E6*0.03 | F7: =revenue!F6*0.03
A8: Итого операционные расходы, тенге | B8: =SUM(B2:B7) | C8: =SUM(C2:C7) | D8: =SUM(D2:D7) | E8: =SUM(E2:E7) | F8: =SUM(F2:F7)

Sheet Отчет о прибылях и убытках
A1: P&L | B1: Год 1 | C1: Год 2 | D1: Год 3 | E1: Год 4 | F1: Год 5
A2: Выручка, тенге | B2: =revenue!B6 | C2: =revenue!C6 | D2: =revenue!D6 | E2: =revenue!E6 | F2: =revenue!F6
A3: Операционные расходы, тенге | B3: =expenses!B8 | C3: =expenses!C8 | D3: =expenses!D8 | E3: =expenses!E8 | F3: =expenses!F8
A4: EBITDA, тенге | B4: =B2-B3 | C4: =C2-C3 | D4: =D2-D3 | E4: =E2-E3 | F4: =F2-F3
A5: Амортизация, тенге | B5: 200000 | C5: 200000 | D5: 200000 | E5: 200000 | F5: 200000
A6: EBIT, тенге | B6: =B4-B5 | C6: =C4-C5 | D6: =D4-D5 | E6: =E4-E5 | F6: =F4-F5
A7: Налоги, тенге | B7: =IF(B6>0,B6*assumptions!B2,0) | C7: =IF(C6>0,C6*assumptions!B2,0) | D7: =IF(D6>0,D6*assumptions!B2,0) | E7: =IF(E6>0,E6*assumptions!B2,0) | F7: =IF(F6>0,F6*assumptions!B2,0)
A8: Чистая прибыль, тенге | B8: =B6-B7 | C8: =C6-C7 | D8: =D6-D7 | E8: =E6-E7 | F8: =F6-F7
A9: Рентабельность по чистой прибыли, % | B9: =IF(B2>0,B8/B2*100,0) | C9: =IF(C2>0,C8/C2*100,0) | D9: =IF(D2>0,D8/D2*100,0) | E9: =IF(E2>0,E8/E2*100,0) | F9: =IF(F2>0,F8/F2*100,0)
